cached_http_fetcher/__init__.py
cached_http_fetcher/content.py
cached_http_fetcher/entrypoint.py
cached_http_fetcher/meta.py
cached_http_fetcher/model.py
cached_http_fetcher/rate_limit_fetcher.py
cached_http_fetcher/request.py
cached_http_fetcher/url_list.py
cached_http_fetcher/storage/__init__.py
cached_http_fetcher/storage/base.py
cached_http_fetcher/storage/memory.py
cached_http_fetcher-0.1.6.dist-info/LICENSE
cached_http_fetcher-0.1.6.dist-info/METADATA
cached_http_fetcher-0.1.6.dist-info/WHEEL
cached_http_fetcher-0.1.6.dist-info/top_level.txt
cached_http_fetcher-0.1.6.dist-info/RECORD
