Metadata-Version: 2.1
Name: cached-http-fetcher
Version: 0.1.6
Summary: A cached http fetcher
Home-page: https://github.com/gunyarakun/cached-http-fetcher
Author: Tasuku SUENAGA a.k.a. gunyarakun
Author-email: tasuku-s-github@titech.ac
License: MIT License
Platform: UNKNOWN
Requires-Python: >=3.7
Requires-Dist: requests
Provides-Extra: test
Requires-Dist: pytest (~=6.2.2) ; extra == 'test'
Requires-Dist: pytest-cov (~=2.11.1) ; extra == 'test'
Requires-Dist: pytest-mock (~=3.5.1) ; extra == 'test'
Requires-Dist: responses (~=0.13.1) ; extra == 'test'
Requires-Dist: pysen (~=0.9.1) ; extra == 'test'
